odoo/addons/l10n_de_location_nuts/README.rst
odoo/addons/l10n_de_location_nuts/__init__.py
odoo/addons/l10n_de_location_nuts/__manifest__.py
odoo/addons/l10n_de_location_nuts/hooks.py
odoo/addons/l10n_de_location_nuts/i18n/es.po
odoo/addons/l10n_de_location_nuts/i18n/l10n_de_location_nuts.pot
odoo/addons/l10n_de_location_nuts/static/description/icon.png
odoo/addons/l10n_de_location_nuts/wizard/__init__.py
odoo/addons/l10n_de_location_nuts/wizard/nuts_import.py
odoo11_addon_l10n_de_location_nuts-11.0.1.0.0.99.dev1.dist-info/DESCRIPTION.rst
odoo11_addon_l10n_de_location_nuts-11.0.1.0.0.99.dev1.dist-info/METADATA
odoo11_addon_l10n_de_location_nuts-11.0.1.0.0.99.dev1.dist-info/RECORD
odoo11_addon_l10n_de_location_nuts-11.0.1.0.0.99.dev1.dist-info/WHEEL
odoo11_addon_l10n_de_location_nuts-11.0.1.0.0.99.dev1.dist-info/metadata.json
odoo11_addon_l10n_de_location_nuts-11.0.1.0.0.99.dev1.dist-info/top_level.txt
